MANIFEST.in
README
setup.cfg
setup.py
btk/__init__.py
btk/_btk.so
btk.egg-info/PKG-INFO
btk.egg-info/SOURCES.txt
btk.egg-info/dependency_links.txt
btk.egg-info/entry_points.txt
btk.egg-info/not-zip-safe
btk.egg-info/requires.txt
btk.egg-info/top_level.txt