Metadata-Version: 1.1
Name: btk
Version: 0.3.0
Summary: Python binding for the C++ library Biomechanical ToolKit (BTK)
Home-page: https://code.google.com/p/b-tk/
Author: Arnaud Barré
Author-email: arnaud.barre@gmail.com
License: New BSD License
Keywords: motion capture gait analysis C3D btk
Platform: UNKNOWN
Classifier: Programming Language :: C++
Classifier: Topic :: Scientific/Engineering :: Medical Science Apps.
Classifier: Programming Language :: Python :: 2.7
Classifier: Operating System :: MacOS :: MacOS X
Classifier: License :: OSI Approved :: BSD License
Classifier: Development Status :: 5 - Production/Stable
